nameko_mongo_util/__init__.py
nameko_mongo_util/mongo_provider.py
nameko_mongo_util/mongo_util.py
nameko_mongo_util-1.0.1.dist-info/METADATA
nameko_mongo_util-1.0.1.dist-info/RECORD
nameko_mongo_util-1.0.1.dist-info/WHEEL
nameko_mongo_util-1.0.1.dist-info/top_level.txt
